psus/__init__.py
psus/__main__.py
psus-1.0.1.dist-info/METADATA
psus-1.0.1.dist-info/WHEEL
psus-1.0.1.dist-info/entry_points.txt
psus-1.0.1.dist-info/licenses/LICENSE
psus-1.0.1.dist-info/RECORD
