Metadata-Version: 2.1
Name: psus
Version: 1.0.1
Summary: Script to send suspend/continue signals to processes through psutil
Project-URL: Homepage, https://github.com/4ndrs/psus
Project-URL: Bug Tracker, https://github.com/4ndrs/psus/issues
Author-email: 4ndrs <andres.degozaru@gmail.com>
License: MIT License
Classifier: License :: OSI Approved :: MIT License
Classifier: Operating System :: POSIX :: Linux
Classifier: Programming Language :: Python :: 3
Requires-Python: >=3.10
Requires-Dist: psutil~=5.9.1
